README.rst
setup.py
zabbops/__init__.py
zabbops/configurator.py
zabbops/transform.py
zabbops.egg-info/PKG-INFO
zabbops.egg-info/SOURCES.txt
zabbops.egg-info/dependency_links.txt
zabbops.egg-info/not-zip-safe
zabbops.egg-info/requires.txt
zabbops.egg-info/top_level.txt