Metadata-Version: 1.0
Name: zabbops
Version: 1.1
Summary: Zabbix/AWS orchestration
Home-page: http://github.com/cavaliercoder/zabbops
Author: Ryan Armstrong
Author-email: ryan@cavaliercoder.com
License: GPLv3
Platform: UNKNOWN
